h7_env_manager/__init__.py
h7_env_manager/env_manager.py
h7_env_manager-1.0.2.dist-info/METADATA
h7_env_manager-1.0.2.dist-info/WHEEL
h7_env_manager-1.0.2.dist-info/top_level.txt
h7_env_manager-1.0.2.dist-info/RECORD
