Metadata-Version: 2.4
Name: h7-env-manager
Version: 1.0.2
Summary: Core utility classes for environment variable management in Python projects
Author-email: Roger Mori <roger.mori@example.com>
License: MIT
Project-URL: Homepage, https://github.com/rogermori/h7-env-manager
Project-URL: Bug Tracker, https://github.com/rogermori/h7-env-manager/issues
Classifier: Programming Language :: Python :: 3
Classifier: License :: OSI Approved :: MIT License
Classifier: Operating System :: OS Independent
Requires-Python: >=3.7
Requires-Dist: python-dotenv>=0.19.0
Requires-Dist: h7-file-finder>=1.0.1
